dsslab/net_bench/__init__.py
dsslab/net_bench/attrs.py
dsslab/net_bench/draw.py
dsslab/net_bench/forgeimporter.py
dsslab/net_bench/graphdescriptor.py
dsslab/net_bench/graphimporter.py
dsslab/net_bench/imagecollection.py
dsslab/net_bench/layouter.py
dsslab/net_bench/log/__init__.py
dsslab/net_bench/log/config.json
dsslab/net_bench/log/logger.py
dsslab/net_bench/log/logs/.gitkeep
dsslab/net_bench/mapping.py
dsslab/net_bench/supplier.py
dsslab/net_bench/textsearch.py
dsslab/net_bench/utils.py
dsslab/net_bench/wdc.py
dsslab_net_bench-0.12.3.dist-info/METADATA
dsslab_net_bench-0.12.3.dist-info/WHEEL
dsslab_net_bench-0.12.3.dist-info/licenses/LICENSE
dsslab_net_bench-0.12.3.dist-info/RECORD
