Metadata-Version: 2.4
Name: dsslab-net-bench
Version: 0.12.3
Summary: An opiniated wrapper around NetworkX to help with drawing and positioning.
License-File: LICENSE
Author: David Seseke
Author-email: david.seseke@uni-hamburg.de
Requires-Python: >=3.10,<4.0
Classifier: Programming Language :: Python :: 3
Classifier: Programming Language :: Python :: 3.10
Classifier: Programming Language :: Python :: 3.11
Classifier: Programming Language :: Python :: 3.12
Classifier: Programming Language :: Python :: 3.13
Classifier: Programming Language :: Python :: 3.14
Provides-Extra: graphviz
Requires-Dist: matplotlib (>=3.5.2,<4.0.0)
Requires-Dist: networkx (>=3.4,<4.0)
Requires-Dist: numpy (>=1.26,<2.0) ; python_version < "3.13"
Requires-Dist: numpy (>=2,<3) ; python_version >= "3.13"
Requires-Dist: openpyxl (>=3.1.5,<4.0.0)
Requires-Dist: ordered-set (>=4.1.0,<5.0.0)
Requires-Dist: pandas (>=2.2,<3.0)
Requires-Dist: pygraphviz (>=1.11,<2.0) ; extra == "graphviz"
Requires-Dist: python-pptx (>=1.0.2,<2.0.0)
Requires-Dist: requests (>=2.28.1,<3.0.0)
Requires-Dist: scipy (>=1.13,<2.0) ; python_version < "3.13"
Requires-Dist: scipy (>=1.15,<2.0) ; python_version >= "3.13"
Requires-Dist: strenum (>=0.4.15,<0.5.0) ; python_version < "3.11"
